{"is_source_file": true, "format": "html", "description": ".html file: index.html", "external_files": [], "external_methods": [], "published": [], "classes": [], "methods": [], "calls": [], "search-terms": ["index.html", "html"], "state": 2, "file_id": 9, "knowledge_revision": 42, "git_revision": "dbf8b6a5f837d72eb016d1e319794f515fa5f381", "revision_history": [{"22": "dbf8b6a5f837d72eb016d1e319794f515fa5f381"}, {"42": "dbf8b6a5f837d72eb016d1e319794f515fa5f381"}], "filename": "lms_frontend/public/index.html", "format-version": 4, "code-base-name": "https://github.com/kavia-common/interactive-learning-platform-222543-222565.git:kavia-main"}